{
  "buildCommand" : "build",
  "configuredTargets" : [
    {
      "guid" : "f8296182cb4f3f7f451cf332984d8bd68f95ff5d3f8bd6ef4f060898c0ff49e9"
    }
  ],
  "continueBuildingAfterErrors" : false,
  "enableIndexBuildArena" : false,
  "hideShellScriptEnvironment" : false,
  "parameters" : {
    "action" : "build",
    "activeArchitecture" : "arm64",
    "activeRunDestination" : {
      "disableOnlyActiveArch" : false,
      "platform" : "iphonesimulator",
      "sdk" : "iphonesimulator14.5",
      "sdkVariant" : "iphonesimulator",
      "supportedArchitectures" : [
        "arm64",
        "x86_64"
      ],
      "targetArchitecture" : "arm64"
    },
    "arenaInfo" : {
      "buildIntermediatesPath" : "/Users/shikha/Downloads/Location 2/Build/Intermediates.noindex",
      "buildProductsPath" : "/Users/shikha/Downloads/Location 2/Build/Products",
      "derivedDataPath" : "/Users/shikha/Library/Developer/Xcode/DerivedData",
      "indexDataStoreFolderPath" : "/Users/shikha/Library/Developer/Xcode/DerivedData/Location-hekavppkbqikkdhbmqgzcpylhbxe/Index/DataStore",
      "indexEnableDataStore" : true,
      "indexPCHPath" : "/Users/shikha/Library/Developer/Xcode/DerivedData/Location-hekavppkbqikkdhbmqgzcpylhbxe/Index/PrecompiledHeaders",
      "pchPath" : "/Users/shikha/Downloads/Location 2/Build/Intermediates.noindex/PrecompiledHeaders"
    },
    "configurationName" : "Debug",
    "overrides" : {
      "synthesized" : {
        "table" : {
          "ASSETCATALOG_FILTER_FOR_DEVICE_MODEL" : "iPhone10,4",
          "ASSETCATALOG_FILTER_FOR_DEVICE_OS_VERSION" : "14.5",
          "BUILD_ACTIVE_RESOURCES_ONLY" : "YES",
          "ENABLE_PREVIEWS" : "NO",
          "TARGET_DEVICE_IDENTIFIER" : "932BE92A-69D1-40AF-9373-DA74D0A991AE",
          "TARGET_DEVICE_MODEL" : "iPhone10,4",
          "TARGET_DEVICE_OS_VERSION" : "14.5",
          "TARGET_DEVICE_PLATFORM_NAME" : "iphonesimulator"
        }
      }
    }
  },
  "schemeCommand" : "launch",
  "shouldCollectMetrics" : false,
  "showNonLoggedProgress" : true,
  "useDryRun" : false,
  "useImplicitDependencies" : true,
  "useLegacyBuildLocations" : false,
  "useParallelTargets" : true
}